nonebot_plugin_pam/__init__.py
nonebot_plugin_pam/checker.py
nonebot_plugin_pam/command.py
nonebot_plugin_pam/config.py
nonebot_plugin_pam/paimon.py
nonebot_plugin_pam/ratelimit.py
nonebot_plugin_pam/server.py
nonebot_plugin_pam/utils.py
nonebot_plugin_pam-0.2.3.dist-info/LICENSE
nonebot_plugin_pam-0.2.3.dist-info/METADATA
nonebot_plugin_pam-0.2.3.dist-info/WHEEL
nonebot_plugin_pam-0.2.3.dist-info/RECORD
