Metadata-Version: 2.1
Name: nonebot-plugin-pam
Version: 0.2.3
Summary: Nonebot 2 的权限与访问管理。
License: Apache-2.0
Author: Yan
Author-email: 1964649083@qq.com
Requires-Python: >=3.11,<4.0
Classifier: License :: OSI Approved :: Apache Software License
Classifier: Programming Language :: Python :: 3
Classifier: Programming Language :: Python :: 3.11
Classifier: Programming Language :: Python :: 3.12
Classifier: Programming Language :: Python :: 3.13
Requires-Dist: fastapi (>=0.115.4,<0.116.0)
Requires-Dist: nonebot-plugin-apscheduler (>=0.5.0,<0.6.0)
Requires-Dist: nonebot2 (>=2.4.0,<3.0.0)
Requires-Dist: pyyaml (>=6.0.2,<7.0.0)
